odoo8_addon_base_business_document_import_stock-8.0.1.0.0.99.dev4-nspkg.pth
odoo_addons/base_business_document_import_stock/README.rst
odoo_addons/base_business_document_import_stock/__init__.py
odoo_addons/base_business_document_import_stock/__openerp__.py
odoo_addons/base_business_document_import_stock/i18n/base_business_document_import_stock.pot
odoo_addons/base_business_document_import_stock/models/__init__.py
odoo_addons/base_business_document_import_stock/models/business_document_import.py
odoo_addons/base_business_document_import_stock/static/description/icon.png
odoo_addons/base_business_document_import_stock/tests/__init__.py
odoo_addons/base_business_document_import_stock/tests/test_incoterm_match.py
odoo8_addon_base_business_document_import_stock-8.0.1.0.0.99.dev4.dist-info/METADATA
odoo8_addon_base_business_document_import_stock-8.0.1.0.0.99.dev4.dist-info/WHEEL
odoo8_addon_base_business_document_import_stock-8.0.1.0.0.99.dev4.dist-info/namespace_packages.txt
odoo8_addon_base_business_document_import_stock-8.0.1.0.0.99.dev4.dist-info/top_level.txt
odoo8_addon_base_business_document_import_stock-8.0.1.0.0.99.dev4.dist-info/RECORD
